LICENSE
README.md
setup.py
czlib/__init__.py
czlib/czlib.py
czlib/czlib_dir.py
czlib/czlib_file.py
czlib/serialize.py
czlib/signature.py
czlib.egg-info/PKG-INFO
czlib.egg-info/SOURCES.txt
czlib.egg-info/dependency_links.txt
czlib.egg-info/requires.txt
czlib.egg-info/top_level.txt