Metadata-Version: 2.1
Name: czlib
Version: 2.1.1
Home-page: https://github.com/khanh101/czlib
Author: Nguyen Ngoc Khanh
Author-email: khanh.nguyen.contact@gmail.com
License: MIT
License-File: LICENSE
